weixin_api/__init__.py
weixin_api/auth.py
weixin_api/base.py
weixin_api/helper.py
weixin_api/media.py
weixin_api/message.py
weixin_api/midas.py
weixin_api/qrcode.py
weixin_api/request.py
weixin_api/template.py
weixin_api/ticket.py
weixin_api/wxa.py
weixin_api/sns/__init__.py
weixin_api/sns/oauth2/__init__.py
weixin_api-1.4.0.dist-info/METADATA
weixin_api-1.4.0.dist-info/RECORD
weixin_api-1.4.0.dist-info/WHEEL
weixin_api-1.4.0.dist-info/top_level.txt
