Metadata-Version: 2.1
Name: weixin-api
Version: 1.4.0
Summary: weixin api for miniprogram and minigame
Home-page: https://github.com/kerol/weixin-api
Author: kerol
Author-email: ikerol@163.com
License: UNKNOWN
Platform: UNKNOWN
Classifier: Programming Language :: Python :: 3
Classifier: License :: OSI Approved :: MIT License
Classifier: Operating System :: OS Independent
Requires-Dist: requests
Requires-Dist: ujson
Requires-Dist: pycrypto
